ram.v
// Main memory using RTL instead of gate level modeling.
`timescale 1ns / 1ps

module ram(
    input [7:0] a,        // memory address
    input sa,             // set memory address in memory address register
    input s,              // set data in memory at address
    input e,              // enable data out from memory at address
    inout [7:0] bus       // 8-bit data to/from data bus
);

    // Memory Address Register (MAR)
    reg [7:0] addr_reg;

    // Random Access Memory (RAM)
    reg [7:0] mem_reg[0:255]; // 256 memory addresses

    // Set address register
    always @*
        if (sa == 1'b1)
            addr_reg <= a;

    // Data Input
    always @*
        if (s == 1'b1)
            mem_reg[addr_reg] <= bus;

    assign bus = e ? mem_reg[addr_reg] : 8'bz;
endmodule

ram_TB.v
module ram_TB;

// Test Bench Variables
reg [7:0] a;
reg sa, s, e;
reg [7:0] bus_reg;
wire [7:0] bus_wire;
integer i; // for loop iterator

assign bus_wire = s ? bus_reg : 8'bz; // drive bus wire only when setting memory

// Instantiate device under test
ram DUT(
    .a(a),        // current memory address
    .sa(sa),      // set memory address in memory address register
    .s(s),        // set data in memory at current address
    .e(e),        // enable data out from memory at address
    .bus(bus_wire) // 8-bit data bus
);

initial begin
    $dumpfile("ram.vcd");
    $dumpvars(0, ram_TB);

    // Initialize values
    a = 8'b0;
    sa = 0;
    s = 0;
    e = 0;
    bus_reg = 8'b0;

    // Conduct test sequence
    // Load RAM with values
    for(i = 0; i < 256; i++) begin
        a = i;         // start at address value 0
        #1 sa = 1;     // latch address value in address register
        #1 sa = 0;

        bus_reg = i + 1; // put address value plus 1 in bus reg
        #1 s = 1;         // load data in reg to memory at address reg
        #1 s = 0;
    end

    // Read values from RAM
    for(i = 0; i < 256; i++) begin
        a = i;         // start at address value 0
        #1 sa = 1;     // latch address value in address register
        #1 sa = 0;

        #1 e = 1;      // read out data at memory address reg
        #1 e = 0;
    end

    $finish;
end

endmodule

ram.vcd
$date
	Sun Jul 06 19:30:10 2025
$end
$version
	Icarus Verilog
$end
$timescale
	1ps
$end
$scope module ram_TB $end
$var wire 8 ! bus_wire [7:0] $end
$var reg 8 " a [7:0] $end
$var reg 8 # bus_reg [7:0] $end
$var reg 1 $ e $end
$var reg 1 % s $end
$var reg 1 & sa $end
$var integer 32 ' i [31:0] $end
$scope module DUT $end
$var wire 8 ( a [7:0] $end
$var wire 8 ) bus [7:0] $end
$var wire 1 $ e $end
$var wire 1 % s $end
$var wire 1 & sa $end
$var reg 8 * addr_reg [7:0] $end
$upscope $end
$upscope $end
$enddefinitions $end
$comment Show the parameter values. $end
$dumpall
$end
#0
$dumpvars
bx *
bz )
b0 (
b0 '
0&
0%
0$
b0 #
b0 "
bz !
$end
#1000
b0 *
1&
#2000
b1 #
0&
#3000
b1 !
b1 )
1%
#4000
bz !
bz )
b1 "
b1 (
b1 '
0%
#5000
b1 *
1&
#6000
b10 #
0&
#7000
b10 !
b10 )
1%
#8000
bz !
bz )
b10 "
b10 (
b10 '
0%
#9000
b10 *
1&
#10000
b11 #
0&
#11000
b11 !
b11 )
1%
#12000
bz !
bz )
b11 "
b11 (
b11 '
0%
#13000
b11 *
1&
#14000
b100 #
0&
#15000
b100 !
b100 )
1%
#16000
bz !
bz )
b100 "
b100 (
b100 '
0%
#17000
b100 *
1&
#18000
b101 #
0&
#19000
b101 !
b101 )
1%
#20000
bz !
bz )
b101 "
b101 (
b101 '
0%
#21000
b101 *
1&
#22000
b110 #
0&
#23000
b110 !
b110 )
1%
#24000
bz !
bz )
b110 "
b110 (
b110 '
0%
#25000
b110 *
1&
#26000
b111 #
0&
#27000
b111 !
b111 )
1%
#28000
bz !
bz )
b111 "
b111 (
b111 '
0%
#29000
b111 *
1&
#30000
b1000 #
0&
#31000
b1000 !
b1000 )
1%
#32000
bz !
bz )
b1000 "
b1000 (
b1000 '
0%
#33000
b1000 *
1&
#34000
b1001 #
0&
#35000
b1001 !
b1001 )
1%
#36000
bz !
bz )
b1001 "
b1001 (
b1001 '
0%
#37000
b1001 *
1&
#38000
b1010 #
0&
#39000
b1010 !
b1010 )
1%
#40000
bz !
bz )
b1010 "
b1010 (
b1010 '
0%
#41000
b1010 *
1&
#42000
b1011 #
0&
#43000
b1011 !
b1011 )
1%
#44000
bz !
bz )
b1011 "
b1011 (
b1011 '
0%
#45000
b1011 *
1&
#46000
b1100 #
0&
#47000
b1100 !
b1100 )
1%
#48000
bz !
bz )
b1100 "
b1100 (
b1100 '
0%
#49000
b1100 *
1&
#50000
b1101 #
0&
#51000
b1101 !
b1101 )
1%
#52000
bz !
bz )
b1101 "
b1101 (
b1101 '
0%
#53000
b1101 *
1&
#54000
b1110 #
0&
#55000
b1110 !
b1110 )
1%
#56000
bz !
bz )
b1110 "
b1110 (
b1110 '
0%
#57000
b1110 *
1&
#58000
b1111 #
0&
#59000
b1111 !
b1111 )
1%
#60000
bz !
bz )
b1111 "
b1111 (
b1111 '
0%
#61000
b1111 *
1&
#62000
b10000 #
0&
#63000
b10000 !
b10000 )
1%
#64000
bz !
bz )
b10000 "
b10000 (
b10000 '
0%
#65000
b10000 *
1&
#66000
b10001 #
0&
#67000
b10001 !
b10001 )
1%
#68000
bz !
bz )
b10001 "
b10001 (
b10001 '
0%
#69000
b10001 *
1&
#70000
b10010 #
0&
#71000
b10010 !
b10010 )
1%
#72000
bz !
bz )
b10010 "
b10010 (
b10010 '
0%
#73000
b10010 *
1&
#74000
b10011 #
0&
#75000
b10011 !
b10011 )
1%
#76000
bz !
bz )
b10011 "
b10011 (
b10011 '
0%
#77000
b10011 *
1&
#78000
b10100 #
0&
#79000
b10100 !
b10100 )
1%
#80000
bz !
bz )
b10100 "
b10100 (
b10100 '
0%
#81000
b10100 *
1&
#82000
b10101 #
0&
#83000
b10101 !
b10101 )
1%
#84000
bz !
bz )
b10101 "
b10101 (
b10101 '
0%
#85000
b10101 *
1&
#86000
b10110 #
0&
#87000
b10110 !
b10110 )
1%
#88000
bz !
bz )
b10110 "
b10110 (
b10110 '
0%
#89000
b10110 *
1&
#90000
b10111 #
0&
#91000
b10111 !
b10111 )
1%
#92000
bz !
bz )
b10111 "
b10111 (
b10111 '
0%
#93000
b10111 *
1&
#94000
b11000 #
0&
#95000
b11000 !
b11000 )
1%
#96000
bz !
bz )
b11000 "
b11000 (
b11000 '
0%
#97000
b11000 *
1&
#98000
b11001 #
0&
#99000
b11001 !
b11001 )
1%
#100000
bz !
bz )
b11001 "
b11001 (
b11001 '
0%
#101000
b11001 *
1&
#102000
b11010 #
0&
#103000
b11010 !
b11010 )
1%
#104000
bz !
bz )
b11010 "
b11010 (
b11010 '
0%
#105000
b11010 *
1&
#106000
b11011 #
0&
#107000
b11011 !
b11011 )
1%
#108000
bz !
bz )
b11011 "
b11011 (
b11011 '
0%
#109000
b11011 *
1&
#110000
b11100 #
0&
#111000
b11100 !
b11100 )
1%
#112000
bz !
bz )
b11100 "
b11100 (
b11100 '
0%
#113000
b11100 *
1&
#114000
b11101 #
0&
#115000
b11101 !
b11101 )
1%
#116000
bz !
bz )
b11101 "
b11101 (
b11101 '
0%
#117000
b11101 *
1&
#118000
b11110 #
0&
#119000
b11110 !
b11110 )
1%
#120000
bz !
bz )
b11110 "
b11110 (
b11110 '
0%
#121000
b11110 *
1&
#122000
b11111 #
0&
#123000
b11111 !
b11111 )
1%
#124000
bz !
bz )
b11111 "
b11111 (
b11111 '
0%
#125000
b11111 *
1&
#126000
b100000 #
0&
#127000
b100000 !
b100000 )
1%
#128000
bz !
bz )
b100000 "
b100000 (
b100000 '
0%
#129000
b100000 *
1&
#130000
b100001 #
0&
#131000
b100001 !
b100001 )
1%
#132000
bz !
bz )
b100001 "
b100001 (
b100001 '
0%
#133000
b100001 *
1&
#134000
b100010 #
0&
#135000
b100010 !
b100010 )
1%
#136000
bz !
bz )
b100010 "
b100010 (
b100010 '
0%
#137000
b100010 *
1&
#138000
b100011 #
0&
#139000
b100011 !
b100011 )
1%
#140000
bz !
bz )
b100011 "
b100011 (
b100011 '
0%
#141000
b100011 *
1&
#142000
b100100 #
0&
#143000
b100100 !
b100100 )
1%
#144000
bz !
bz )
b100100 "
b100100 (
b100100 '
0%
#145000
b100100 *
1&
#146000
b100101 #
0&
#147000
b100101 !
b100101 )
1%
#148000
bz !
bz )
b100101 "
b100101 (
b100101 '
0%
#149000
b100101 *
1&
#150000
b100110 #
0&
#151000
b100110 !
b100110 )
1%
#152000
bz !
bz )
b100110 "
b100110 (
b100110 '
0%
#153000
b100110 *
1&
#154000
b100111 #
0&
#155000
b100111 !
b100111 )
1%
#156000
bz !
bz )
b100111 "
b100111 (
b100111 '
0%
#157000
b100111 *
1&
#158000
b101000 #
0&
#159000
b101000 !
b101000 )
1%
#160000
bz !
bz )
b101000 "
b101000 (
b101000 '
0%
#161000
b101000 *
1&
#162000
b101001 #
0&
#163000
b101001 !
b101001 )
1%
#164000
bz !
bz )
b101001 "
b101001 (
b101001 '
0%
#165000
b101001 *
1&
#166000
b101010 #
0&
#167000
b101010 !
b101010 )
1%
#168000
bz !
bz )
b101010 "
b101010 (
b101010 '
0%
#169000
b101010 *
1&
#170000
b101011 #
0&
#171000
b101011 !
b101011 )
1%
#172000
bz !
bz )
b101011 "
b101011 (
b101011 '
0%
#173000
b101011 *
1&
#174000
b101100 #
0&
#175000
b101100 !
b101100 )
1%
#176000
bz !
bz )
b101100 "
b101100 (
b101100 '
0%
#177000
b101100 *
1&
#178000
b101101 #
0&
#179000
b101101 !
b101101 )
1%
#180000
bz !
bz )
b101101 "
b101101 (
b101101 '
0%
#181000
b101101 *
1&
#182000
b101110 #
0&
#183000
b101110 !
b101110 )
1%
#184000
bz !
bz )
b101110 "
b101110 (
b101110 '
0%
#185000
b101110 *
1&
#186000
b101111 #
0&
#187000
b101111 !
b101111 )
1%
#188000
bz !
bz )
b101111 "
b101111 (
b101111 '
0%
#189000
b101111 *
1&
#190000
b110000 #
0&
#191000
b110000 !
b110000 )
1%
#192000
bz !
bz )
b110000 "
b110000 (
b110000 '
0%
#193000
b110000 *
1&
#194000
b110001 #
0&
#195000
b110001 !
b110001 )
1%
#196000
bz !
bz )
b110001 "
b110001 (
b110001 '
0%
#197000
b110001 *
1&
#198000
b110010 #
0&
#199000
b110010 !
b110010 )
1%
#200000
bz !
bz )
b110010 "
b110010 (
b110010 '
0%
#201000
b110010 *
1&
#202000
b110011 #
0&
#203000
b110011 !
b110011 )
1%
#204000
bz !
bz )
b110011 "
b110011 (
b110011 '
0%
#205000
b110011 *
1&
#206000
b110100 #
0&
#207000
b110100 !
b110100 )
1%
#208000
bz !
bz )
b110100 "
b110100 (
b110100 '
0%
#209000
b110100 *
1&
#210000
b110101 #
0&
#211000
b110101 !
b110101 )
1%
#212000
bz !
bz )
b110101 "
b110101 (
b110101 '
0%
#213000
b110101 *
1&
#214000
b110110 #
0&
#215000
b110110 !
b110110 )
1%
#216000
bz !
bz )
b110110 "
b110110 (
b110110 '
0%
#217000
b110110 *
1&
#218000
b110111 #
0&
#219000
b110111 !
b110111 )
1%
#220000
bz !
bz )
b110111 "
b110111 (
b110111 '
0%
#221000
b110111 *
1&
#222000
b111000 #
0&
#223000
b111000 !
b111000 )
1%
#224000
bz !
bz )
b111000 "
b111000 (
b111000 '
0%
#225000
b111000 *
1&
#226000
b111001 #
0&
#227000
b111001 !
b111001 )
1%
#228000
bz !
bz )
b111001 "
b111001 (
b111001 '
0%
#229000
b111001 *
1&
#230000
b111010 #
0&
#231000
b111010 !
b111010 )
1%
#232000
bz !
bz )
b111010 "
b111010 (
b111010 '
0%
#233000
b111010 *
1&
#234000
b111011 #
0&
#235000
b111011 !
b111011 )
1%
#236000
bz !
bz )
b111011 "
b111011 (
b111011 '
0%
#237000
b111011 *
1&
#238000
b111100 #
0&
#239000
b111100 !
b111100 )
1%
#240000
bz !
bz )
b111100 "
b111100 (
b111100 '
0%
#241000
b111100 *
1&
#242000
b111101 #
0&
#243000
b111101 !
b111101 )
1%
#244000
bz !
bz )
b111101 "
b111101 (
b111101 '
0%
#245000
b111101 *
1&
#246000
b111110 #
0&
#247000
b111110 !
b111110 )
1%
#248000
bz !
bz )
b111110 "
b111110 (
b111110 '
0%
#249000
b111110 *
1&
#250000
b111111 #
0&
#251000
b111111 !
b111111 )
1%
#252000
bz !
bz )
b111111 "
b111111 (
b111111 '
0%
#253000
b111111 *
1&
#254000
b1000000 #
0&
#255000
b1000000 !
b1000000 )
1%
#256000
bz !
bz )
b1000000 "
b1000000 (
b1000000 '
0%
#257000
b1000000 *
1&
#258000
b1000001 #
0&
#259000
b1000001 !
b1000001 )
1%
#260000
bz !
bz )
b1000001 "
b1000001 (
b1000001 '
0%
#261000
b1000001 *
1&
#262000
b1000010 #
0&
#263000
b1000010 !
b1000010 )
1%
#264000
bz !
bz )
b1000010 "
b1000010 (
b1000010 '
0%
#265000
b1000010 *
1&
#266000
b1000011 #
0&
#267000
b1000011 !
b1000011 )
1%
#268000
bz !
bz )
b1000011 "
b1000011 (
b1000011 '
0%
#269000
b1000011 *
1&
#270000
b1000100 #
0&
#271000
b1000100 !
b1000100 )
1%
#272000
bz !
bz )
b1000100 "
b1000100 (
b1000100 '
0%
#273000
b1000100 *
1&
#274000
b1000101 #
0&
#275000
b1000101 !
b1000101 )
1%
#276000
bz !
bz )
b1000101 "
b1000101 (
b1000101 '
0%
#277000
b1000101 *
1&
#278000
b1000110 #
0&
#279000
b1000110 !
b1000110 )
1%
#280000
bz !
bz )
b1000110 "
b1000110 (
b1000110 '
0%
#281000
b1000110 *
1&
#282000
b1000111 #
0&
#283000
b1000111 !
b1000111 )
1%
#284000
bz !
bz )
b1000111 "
b1000111 (
b1000111 '
0%
#285000
b1000111 *
1&
#286000
b1001000 #
0&
#287000
b1001000 !
b1001000 )
1%
#288000
bz !
bz )
b1001000 "
b1001000 (
b1001000 '
0%
#289000
b1001000 *
1&
#290000
b1001001 #
0&
#291000
b1001001 !
b1001001 )
1%
#292000
bz !
bz )
b1001001 "
b1001001 (
b1001001 '
0%
#293000
b1001001 *
1&
#294000
b1001010 #
0&
#295000
b1001010 !
b1001010 )
1%
#296000
bz !
bz )
b1001010 "
b1001010 (
b1001010 '
0%
#297000
b1001010 *
1&
#298000
b1001011 #
0&
#299000
b1001011 !
b1001011 )
1%
#300000
bz !
bz )
b1001011 "
b1001011 (
b1001011 '
0%
#301000
b1001011 *
1&
#302000
b1001100 #
0&
#303000
b1001100 !
b1001100 )
1%
#304000
bz !
bz )
b1001100 "
b1001100 (
b1001100 '
0%
#305000
b1001100 *
1&
#306000
b1001101 #
0&
#307000
b1001101 !
b1001101 )
1%
#308000
bz !
bz )
b1001101 "
b1001101 (
b1001101 '
0%
#309000
b1001101 *
1&
#310000
b1001110 #
0&
#311000
b1001110 !
b1001110 )
1%
#312000
bz !
bz )
b1001110 "
b1001110 (
b1001110 '
0%
#313000
b1001110 *
1&
#314000
b1001111 #
0&
#315000
b1001111 !
b1001111 )
1%
#316000
bz !
bz )
b1001111 "
b1001111 (
b1001111 '
0%
#317000
b1001111 *
1&
#318000
b1010000 #
0&
#319000
b1010000 !
b1010000 )
1%
#320000
bz !
bz )
b1010000 "
b1010000 (
b1010000 '
0%
#321000
b1010000 *
1&
#322000
b1010001 #
0&
#323000
b1010001 !
b1010001 )
1%
#324000
bz !
bz )
b1010001 "
b1010001 (
b1010001 '
0%
#325000
b1010001 *
1&
#326000
b1010010 #
0&
#327000
b1010010 !
b1010010 )
1%
#328000
bz !
bz )
b1010010 "
b1010010 (
b1010010 '
0%
#329000
b1010010 *
1&
#330000
b1010011 #
0&
#331000
b1010011 !
b1010011 )
1%
#332000
bz !
bz )
b1010011 "
b1010011 (
b1010011 '
0%
#333000
b1010011 *
1&
#334000
b1010100 #
0&
#335000
b1010100 !
b1010100 )
1%
#336000
bz !
bz )
b1010100 "
b1010100 (
b1010100 '
0%
#337000
b1010100 *
1&
#338000
b1010101 #
0&
#339000
b1010101 !
b1010101 )
1%
#340000
bz !
bz )
b1010101 "
b1010101 (
b1010101 '
0%
#341000
b1010101 *
1&
#342000
b1010110 #
0&
#343000
b1010110 !
b1010110 )
1%
#344000
bz !
bz )
b1010110 "
b1010110 (
b1010110 '
0%
#345000
b1010110 *
1&
#346000
b1010111 #
0&
#347000
b1010111 !
b1010111 )
1%
#348000
bz !
bz )
b1010111 "
b1010111 (
b1010111 '
0%
#349000
b1010111 *
1&
#350000
b1011000 #
0&
#351000
b1011000 !
b1011000 )
1%
#352000
bz !
bz )
b1011000 "
b1011000 (
b1011000 '
0%
#353000
b1011000 *
1&
#354000
b1011001 #
0&
#355000
b1011001 !
b1011001 )
1%
#356000
bz !
bz )
b1011001 "
b1011001 (
b1011001 '
0%
#357000
b1011001 *
1&
#358000
b1011010 #
0&
#359000
b1011010 !
b1011010 )
1%
#360000
bz !
bz )
b1011010 "
b1011010 (
b1011010 '
0%
#361000
b1011010 *
1&
#362000
b1011011 #
0&
#363000
b1011011 !
b1011011 )
1%
#364000
bz !
bz )
b1011011 "
b1011011 (
b1011011 '
0%
#365000
b1011011 *
1&
#366000
b1011100 #
0&
#367000
b1011100 !
b1011100 )
1%
#368000
bz !
bz )
b1011100 "
b1011100 (
b1011100 '
0%
#369000
b1011100 *
1&
#370000
b1011101 #
0&
#371000
b1011101 !
b1011101 )
1%
#372000
bz !
bz )
b1011101 "
b1011101 (
b1011101 '
0%
#373000
b1011101 *
1&
#374000
b1011110 #
0&
#375000
b1011110 !
b1011110 )
1%
#376000
bz !
bz )
b1011110 "
b1011110 (
b1011110 '
0%
#377000
b1011110 *
1&
#378000
b1011111 #
0&
#379000
b1011111 !
b1011111 )
1%
#380000
bz !
bz )
b1011111 "
b1011111 (
b1011111 '
0%
#381000
b1011111 *
1&
#382000
b1100000 #
0&
#383000
b1100000 !
b1100000 )
1%
#384000
bz !
bz )
b1100000 "
b1100000 (
b1100000 '
0%
#385000
b1100000 *
1&
#386000
b1100001 #
0&
#387000
b1100001 !
b1100001 )
1%
#388000
bz !
bz )
b1100001 "
b1100001 (
b1100001 '
0%
#389000
b1100001 *
1&
#390000
b1100010 #
0&
#391000
b1100010 !
b1100010 )
1%
#392000
bz !
bz )
b1100010 "
b1100010 (
b1100010 '
0%
#393000
b1100010 *
1&
#394000
b1100011 #
0&
#395000
b1100011 !
b1100011 )
1%
#396000
bz !
bz )
b1100011 "
b1100011 (
b1100011 '
0%
#397000
b1100011 *
1&
#398000
b1100100 #
0&
#399000
b1100100 !
b1100100 )
1%
#400000
bz !
bz )
b1100100 "
b1100100 (
b1100100 '
0%
#401000
b1100100 *
1&
#402000
b1100101 #
0&
#403000
b1100101 !
b1100101 )
1%
#404000
bz !
bz )
b1100101 "
b1100101 (
b1100101 '
0%
#405000
b1100101 *
1&
#406000
b1100110 #
0&
#407000
b1100110 !
b1100110 )
1%
#408000
bz !
bz )
b1100110 "
b1100110 (
b1100110 '
0%
#409000
b1100110 *
1&
#410000
b1100111 #
0&
#411000
b1100111 !
b1100111 )
1%
#412000
bz !
bz )
b1100111 "
b1100111 (
b1100111 '
0%
#413000
b1100111 *
1&
#414000
b1101000 #
0&
#415000
b1101000 !
b1101000 )
1%
#416000
bz !
bz )
b1101000 "
b1101000 (
b1101000 '
0%
#417000
b1101000 *
1&
#418000
b1101001 #
0&
#419000
b1101001 !
b1101001 )
1%
#420000
bz !
bz )
b1101001 "
b1101001 (
b1101001 '
0%
#421000
b1101001 *
1&
#422000
b1101010 #
0&
#423000
b1101010 !
b1101010 )
1%
#424000
bz !
bz )
b1101010 "
b1101010 (
b1101010 '
0%
#425000
b1101010 *
1&
#426000
b1101011 #
0&
#427000
b1101011 !
b1101011 )
1%
#428000
bz !
bz )
b1101011 "
b1101011 (
b1101011 '
0%
#429000
b1101011 *
1&
#430000
b1101100 #
0&
#431000
b1101100 !
b1101100 )
1%
#432000
bz !
bz )
b1101100 "
b1101100 (
b1101100 '
0%
#433000
b1101100 *
1&
#434000
b1101101 #
0&
#435000
b1101101 !
b1101101 )
1%
#436000
bz !
bz )
b1101101 "
b1101101 (
b1101101 '
0%
#437000
b1101101 *
1&
#438000
b1101110 #
0&
#439000
b1101110 !
b1101110 )
1%
#440000
bz !
bz )
b1101110 "
b1101110 (
b1101110 '
0%
#441000
b1101110 *
1&
#442000
b1101111 #
0&
#443000
b1101111 !
b1101111 )
1%
#444000
bz !
bz )
b1101111 "
b1101111 (
b1101111 '
0%
#445000
b1101111 *
1&
#446000
b1110000 #
0&
#447000
b1110000 !
b1110000 )
1%
#448000
bz !
bz )
b1110000 "
b1110000 (
b1110000 '
0%
#449000
b1110000 *
1&
#450000
b1110001 #
0&
#451000
b1110001 !
b1110001 )
1%
#452000
bz !
bz )
b1110001 "
b1110001 (
b1110001 '
0%
#453000
b1110001 *
1&
#454000
b1110010 #
0&
#455000
b1110010 !
b1110010 )
1%
#456000
bz !
bz )
b1110010 "
b1110010 (
b1110010 '
0%
#457000
b1110010 *
1&
#458000
b1110011 #
0&
#459000
b1110011 !
b1110011 )
1%
#460000
bz !
bz )
b1110011 "
b1110011 (
b1110011 '
0%
#461000
b1110011 *
1&
#462000
b1110100 #
0&
#463000
b1110100 !
b1110100 )
1%
#464000
bz !
bz )
b1110100 "
b1110100 (
b1110100 '
0%
#465000
b1110100 *
1&
#466000
b1110101 #
0&
#467000
b1110101 !
b1110101 )
1%
#468000
bz !
bz )
b1110101 "
b1110101 (
b1110101 '
0%
#469000
b1110101 *
1&
#470000
b1110110 #
0&
#471000
b1110110 !
b1110110 )
1%
#472000
bz !
bz )
b1110110 "
b1110110 (
b1110110 '
0%
#473000
b1110110 *
1&
#474000
b1110111 #
0&
#475000
b1110111 !
b1110111 )
1%
#476000
bz !
bz )
b1110111 "
b1110111 (
b1110111 '
0%
#477000
b1110111 *
1&
#478000
b1111000 #
0&
#479000
b1111000 !
b1111000 )
1%
#480000
bz !
bz )
b1111000 "
b1111000 (
b1111000 '
0%
#481000
b1111000 *
1&
#482000
b1111001 #
0&
#483000
b1111001 !
b1111001 )
1%
#484000
bz !
bz )
b1111001 "
b1111001 (
b1111001 '
0%
#485000
b1111001 *
1&
#486000
b1111010 #
0&
#487000
b1111010 !
b1111010 )
1%
#488000
bz !
bz )
b1111010 "
b1111010 (
b1111010 '
0%
#489000
b1111010 *
1&
#490000
b1111011 #
0&
#491000
b1111011 !
b1111011 )
1%
#492000
bz !
bz )
b1111011 "
b1111011 (
b1111011 '
0%
#493000
b1111011 *
1&
#494000
b1111100 #
0&
#495000
b1111100 !
b1111100 )
1%
#496000
bz !
bz )
b1111100 "
b1111100 (
b1111100 '
0%
#497000
b1111100 *
1&
#498000
b1111101 #
0&
#499000
b1111101 !
b1111101 )
1%
#500000
bz !
bz )
b1111101 "
b1111101 (
b1111101 '
0%
#501000
b1111101 *
1&
#502000
b1111110 #
0&
#503000
b1111110 !
b1111110 )
1%
#504000
bz !
bz )
b1111110 "
b1111110 (
b1111110 '
0%
#505000
b1111110 *
1&
#506000
b1111111 #
0&
#507000
b1111111 !
b1111111 )
1%
#508000
bz !
bz )
b1111111 "
b1111111 (
b1111111 '
0%
#509000
b1111111 *
1&
#510000
b10000000 #
0&
#511000
b10000000 !
b10000000 )
1%
#512000
bz !
bz )
b10000000 "
b10000000 (
b10000000 '
0%
#513000
b10000000 *
1&
#514000
b10000001 #
0&
#515000
b10000001 !
b10000001 )
1%
#516000
bz !
bz )
b10000001 "
b10000001 (
b10000001 '
0%
#517000
b10000001 *
1&
#518000
b10000010 #
0&
#519000
b10000010 !
b10000010 )
1%
#520000
bz !
bz )
b10000010 "
b10000010 (
b10000010 '
0%
#521000
b10000010 *
1&
#522000
b10000011 #
0&
#523000
b10000011 !
b10000011 )
1%
#524000
bz !
bz )
b10000011 "
b10000011 (
b10000011 '
0%
#525000
b10000011 *
1&
#526000
b10000100 #
0&
#527000
b10000100 !
b10000100 )
1%
#528000
bz !
bz )
b10000100 "
b10000100 (
b10000100 '
0%
#529000
b10000100 *
1&
#530000
b10000101 #
0&
#531000
b10000101 !
b10000101 )
1%
#532000
bz !
bz )
b10000101 "
b10000101 (
b10000101 '
0%
#533000
b10000101 *
1&
#534000
b10000110 #
0&
#535000
b10000110 !
b10000110 )
1%
#536000
bz !
bz )
b10000110 "
b10000110 (
b10000110 '
0%
#537000
b10000110 *
1&
#538000
b10000111 #
0&
#539000
b10000111 !
b10000111 )
1%
#540000
bz !
bz )
b10000111 "
b10000111 (
b10000111 '
0%
#541000
b10000111 *
1&
#542000
b10001000 #
0&
#543000
b10001000 !
b10001000 )
1%
#544000
bz !
bz )
b10001000 "
b10001000 (
b10001000 '
0%
#545000
b10001000 *
1&
#546000
b10001001 #
0&
#547000
b10001001 !
b10001001 )
1%
#548000
bz !
bz )
b10001001 "
b10001001 (
b10001001 '
0%
#549000
b10001001 *
1&
#550000
b10001010 #
0&
#551000
b10001010 !
b10001010 )
1%
#552000
bz !
bz )
b10001010 "
b10001010 (
b10001010 '
0%
#553000
b10001010 *
1&
#554000
b10001011 #
0&
#555000
b10001011 !
b10001011 )
1%
#556000
bz !
bz )
b10001011 "
b10001011 (
b10001011 '
0%
#557000
b10001011 *
1&
#558000
b10001100 #
0&
#559000
b10001100 !
b10001100 )
1%
#560000
bz !
bz )
b10001100 "
b10001100 (
b10001100 '
0%
#561000
b10001100 *
1&
#562000
b10001101 #
0&
#563000
b10001101 !
b10001101 )
1%
#564000
bz !
bz )
b10001101 "
b10001101 (
b10001101 '
0%
#565000
b10001101 *
1&
#566000
b10001110 #
0&
#567000
b10001110 !
b10001110 )
1%
#568000
bz !
bz )
b10001110 "
b10001110 (
b10001110 '
0%
#569000
b10001110 *
1&
#570000
b10001111 #
0&
#571000
b10001111 !
b10001111 )
1%
#572000
bz !
bz )
b10001111 "
b10001111 (
b10001111 '
0%
#573000
b10001111 *
1&
#574000
b10010000 #
0&
#575000
b10010000 !
b10010000 )
1%
#576000
bz !
bz )
b10010000 "
b10010000 (
b10010000 '
0%
#577000
b10010000 *
1&
#578000
b10010001 #
0&
#579000
b10010001 !
b10010001 )
1%
#580000
bz !
bz )
b10010001 "
b10010001 (
b10010001 '
0%
#581000
b10010001 *
1&
#582000
b10010010 #
0&
#583000
b10010010 !
b10010010 )
1%
#584000
bz !
bz )
b10010010 "
b10010010 (
b10010010 '
0%
#585000
b10010010 *
1&
#586000
b10010011 #
0&
#587000
b10010011 !
b10010011 )
1%
#588000
bz !
bz )
b10010011 "
b10010011 (
b10010011 '
0%
#589000
b10010011 *
1&
#590000
b10010100 #
0&
#591000
b10010100 !
b10010100 )
1%
#592000
bz !
bz )
b10010100 "
b10010100 (
b10010100 '
0%
#593000
b10010100 *
1&
#594000
b10010101 #
0&
#595000
b10010101 !
b10010101 )
1%
#596000
bz !
bz )
b10010101 "
b10010101 (
b10010101 '
0%
#597000
b10010101 *
1&
#598000
b10010110 #
0&
#599000
b10010110 !
b10010110 )
1%
#600000
bz !
bz )
b10010110 "
b10010110 (
b10010110 '
0%
#601000
b10010110 *
1&
#602000
b10010111 #
0&
#603000
b10010111 !
b10010111 )
1%
#604000
bz !
bz )
b10010111 "
b10010111 (
b10010111 '
0%
#605000
b10010111 *
1&
#606000
b10011000 #
0&
#607000
b10011000 !
b10011000 )
1%
#608000
bz !
bz )
b10011000 "
b10011000 (
b10011000 '
0%
#609000
b10011000 *
1&
#610000
b10011001 #
0&
#611000
b10011001 !
b10011001 )
1%
#612000
bz !
bz )
b10011001 "
b10011001 (
b10011001 '
0%
#613000
b10011001 *
1&
#614000
b10011010 #
0&
#615000
b10011010 !
b10011010 )
1%
#616000
bz !
bz )
b10011010 "
b10011010 (
b10011010 '
0%
#617000
b10011010 *
1&
#618000
b10011011 #
0&
#619000
b10011011 !
b10011011 )
1%
#620000
bz !
bz )
b10011011 "
b10011011 (
b10011011 '
0%
#621000
b10011011 *
1&
#622000
b10011100 #
0&
#623000
b10011100 !
b10011100 )
1%
#624000
bz !
bz )
b10011100 "
b10011100 (
b10011100 '
0%
#625000
b10011100 *
1&
#626000
b10011101 #
0&
#627000
b10011101 !
b10011101 )
1%
#628000
bz !
bz )
b10011101 "
b10011101 (
b10011101 '
0%
#629000
b10011101 *
1&
#630000
b10011110 #
0&
#631000
b10011110 !
b10011110 )
1%
#632000
bz !
bz )
b10011110 "
b10011110 (
b10011110 '
0%
#633000
b10011110 *
1&
#634000
b10011111 #
0&
#635000
b10011111 !
b10011111 )
1%
#636000
bz !
bz )
b10011111 "
b10011111 (
b10011111 '
0%
#637000
b10011111 *
1&
#638000
b10100000 #
0&
#639000
b10100000 !
b10100000 )
1%
#640000
bz !
bz )
b10100000 "
b10100000 (
b10100000 '
0%
#641000
b10100000 *
1&
#642000
b10100001 #
0&
#643000
b10100001 !
b10100001 )
1%
#644000
bz !
bz )
b10100001 "
b10100001 (
b10100001 '
0%
#645000
b10100001 *
1&
#646000
b10100010 #
0&
#647000
b10100010 !
b10100010 )
1%
#648000
bz !
bz )
b10100010 "
b10100010 (
b10100010 '
0%
#649000
b10100010 *
1&
#650000
b10100011 #
0&
#651000
b10100011 !
b10100011 )
1%
#652000
bz !
bz )
b10100011 "
b10100011 (
b10100011 '
0%
#653000
b10100011 *
1&
#654000
b10100100 #
0&
#655000
b10100100 !
b10100100 )
1%
#656000
bz !
bz )
b10100100 "
b10100100 (
b10100100 '
0%
#657000
b10100100 *
1&
#658000
b10100101 #
0&
#659000
b10100101 !
b10100101 )
1%
#660000
bz !
bz )
b10100101 "
b10100101 (
b10100101 '
0%
#661000
b10100101 *
1&
#662000
b10100110 #
0&
#663000
b10100110 !
b10100110 )
1%
#664000
bz !
bz )
b10100110 "
b10100110 (
b10100110 '
0%
#665000
b10100110 *
1&
#666000
b10100111 #
0&
#667000
b10100111 !
b10100111 )
1%
